discord_slash_components_bridge/__init__.py
discord_slash_components_bridge/client.py
discord_slash_components_bridge/const.py
discord_slash_components_bridge/contex.py
discord_slash_components_bridge/dpy_overrides.py
discord_slash_components_bridge/model.py
discord_slash_components_bridge/utils.py
discord_slash_components_bridge-0.1.1.dist-info/LICENSE
discord_slash_components_bridge-0.1.1.dist-info/METADATA
discord_slash_components_bridge-0.1.1.dist-info/WHEEL
discord_slash_components_bridge-0.1.1.dist-info/top_level.txt
discord_slash_components_bridge-0.1.1.dist-info/RECORD
