Metadata-Version: 2.1
Name: discord-slash-components-bridge
Version: 0.1.1
Summary: Library for discord-components and discord-py-interactions(discord-slash).
Home-page: https://github.com/Damego/discord-py-slash-components-bridge
Author: Damego
Author-email: danyabatueff@gmail.com
License: MIT License
Platform: UNKNOWN
Classifier: Intended Audience :: Developers
Classifier: License :: OSI Approved :: MIT License
Classifier: Natural Language :: English
Classifier: Operating System :: OS Independent
Classifier: Programming Language :: Python :: 3
Classifier: Programming Language :: Python :: 3.6
Classifier: Programming Language :: Python :: 3.7
Classifier: Programming Language :: Python :: 3.8
Classifier: Programming Language :: Python :: 3.9
Classifier: Topic :: Internet
Classifier: Topic :: Software Development :: Libraries :: Python Modules
Classifier: Topic :: Software Development :: Libraries
Classifier: Topic :: Utilities
Requires-Python: >=3.6
License-File: LICENSE
Requires-Dist: discord-components
Requires-Dist: discord-py-interactions
